cubicweb_oaipmh/__init__.py
cubicweb_oaipmh/__pkginfo__.py
cubicweb_oaipmh/entities.py
cubicweb_oaipmh/site_cubicweb.py
cubicweb_oaipmh/views.py
cubicweb_oaipmh/i18n/en.po
cubicweb_oaipmh/i18n/fr.po
cubicweb_oaipmh-1.0.1.dist-info/METADATA
cubicweb_oaipmh-1.0.1.dist-info/WHEEL
cubicweb_oaipmh-1.0.1.dist-info/entry_points.txt
cubicweb_oaipmh-1.0.1.dist-info/top_level.txt
cubicweb_oaipmh-1.0.1.dist-info/RECORD
