Metadata-Version: 2.1
Name: cubicweb-oaipmh
Version: 1.0.1
Summary: OAI-PMH server for CubicWeb
Home-page: https://forge.extranet.logilab.fr/cubicweb/cubes/cubicweb-oaipmh
Author: LOGILAB S.A. (Paris, FRANCE)
Author-email: contact@logilab.fr
License: LGPL
Classifier: Environment :: Web Environment
Classifier: Framework :: CubicWeb
Classifier: Programming Language :: Python :: 3
Classifier: Programming Language :: JavaScript
Requires-Python: >= 3.5
Requires-Dist: cubicweb <5.0.0,>=4.0.0
Requires-Dist: cubicweb-web <2.0.0,>=1.0.0
Requires-Dist: python-dateutil
Requires-Dist: isodate
Requires-Dist: pytz
Requires-Dist: lxml
